{
  "date": "2026-04-15",
  "etf_data": {
    "IVV": {
      "price": 65.05,
      "one_yr_ret": 15.607774376414074,
      "ytd_ret": -5.074005569055073,
      "vol_1y": 12.844740327661434,
      "sharpe_1y": 0.9,
      "sortino_1y": 1.24,
      "max_drawdown": -95.6,
      "curr_drawdown": -73.4,
      "from_high": -7.177511415525116
    },
    "FANG": {
      "price": 32.28,
      "one_yr_ret": 18.585868072773714,
      "ytd_ret": -9.79380970296485,
      "vol_1y": 21.684701747689335,
      "sharpe_1y": 0.67,
      "sortino_1y": 1.03,
      "max_drawdown": -42.1,
      "curr_drawdown": -18.4,
      "from_high": -16.329704510108858
    },
    "VAS": {
      "price": 111.22,
      "one_yr_ret": 19.314396803075073,
      "ytd_ret": 3.396433456084713,
      "vol_1y": 11.405283633861723,
      "sharpe_1y": 1.34,
      "sortino_1y": 1.86,
      "max_drawdown": -35.8,
      "curr_drawdown": -2.0,
      "from_high": -2.6520787746170686
    },
    "QAU": {
      "price": 38.34,
      "one_yr_ret": 45.39921057768763,
      "ytd_ret": 8.233279319051444,
      "vol_1y": 28.722414826598385,
      "sharpe_1y": 1.44,
      "sortino_1y": 1.69,
      "max_drawdown": -42.7,
      "curr_drawdown": -14.5,
      "from_high": -13.82333108563722
    },
    "GOLD": {
      "price": 61.98,
      "one_yr_ret": 31.623930509256382,
      "ytd_ret": 2.7008985399274765,
      "vol_1y": 26.44769858734273,
      "sharpe_1y": 1.04,
      "sortino_1y": 1.25,
      "max_drawdown": -91.6,
      "curr_drawdown": -58.9,
      "from_high": -14.768976897689774
    },
    "VGS": {
      "price": 147.54,
      "one_yr_ret": 16.683390701614442,
      "ytd_ret": -3.915503997209957,
      "vol_1y": 11.456795259119279,
      "sharpe_1y": 1.11,
      "sortino_1y": 1.53,
      "max_drawdown": -23.4,
      "curr_drawdown": -5.5,
      "from_high": -5.634793732011515
    },
    "SEMI": {
      "price": 29.14,
      "one_yr_ret": 116.76325805559928,
      "ytd_ret": 22.45943728329054,
      "vol_1y": 30.376397160479236,
      "sharpe_1y": 3.71,
      "sortino_1y": 5.26,
      "max_drawdown": -38.9,
      "curr_drawdown": 0.0,
      "from_high": -0.30790283954840864
    },
    "GDX": {
      "price": 144.2,
      "one_yr_ret": 80.27284007853999,
      "ytd_ret": 8.043813932197041,
      "vol_1y": 43.8272968560727,
      "sharpe_1y": 1.74,
      "sortino_1y": 2.19,
      "max_drawdown": -44.7,
      "curr_drawdown": -15.9,
      "from_high": -17.60000000000001
    },
    "ASIA": {
      "price": 16.66,
      "one_yr_ret": 66.26426642474325,
      "ytd_ret": 8.853116756089886,
      "vol_1y": 27.105223264860705,
      "sharpe_1y": 2.3,
      "sortino_1y": 3.31,
      "max_drawdown": -59.6,
      "curr_drawdown": -2.8,
      "from_high": -1.0688836104513049
    }
  },
  "verdicts": {
    "IVV": "Buy",
    "FANG": "Accumulate",
    "VAS": "Buy",
    "QAU": "Buy",
    "GOLD": "Buy",
    "VGS": "Buy",
    "SEMI": "Strong Buy",
    "GDX": "Accumulate",
    "ASIA": "Strong Buy"
  }
}