{
  "date": "2026-03-17",
  "etf_data": {
    "IVV": {
      "price": 62.9,
      "one_yr_ret": 8.424659915495237,
      "ytd_ret": -7.173177991960267,
      "vol_1y": 16.77826843108134,
      "sharpe_1y": 0.26,
      "sortino_1y": 0.35,
      "max_drawdown": -95.6,
      "curr_drawdown": -73.9,
      "from_high": -10.245433789954337
    },
    "FANG": {
      "price": 30.35,
      "one_yr_ret": 10.341730292810158,
      "ytd_ret": -12.227946089104869,
      "vol_1y": 26.742600087608224,
      "sharpe_1y": 0.24,
      "sortino_1y": 0.35,
      "max_drawdown": -42.1,
      "curr_drawdown": -20.6,
      "from_high": -21.332296526697764
    },
    "VAS": {
      "price": 107.18,
      "one_yr_ret": 12.893076781293345,
      "ytd_ret": -1.0253099837877144,
      "vol_1y": 12.988418148373318,
      "sharpe_1y": 0.68,
      "sortino_1y": 0.85,
      "max_drawdown": -35.8,
      "curr_drawdown": -6.2,
      "from_high": -6.188183807439819
    },
    "QAU": {
      "price": 39.91,
      "one_yr_ret": 65.06764861372018,
      "ytd_ret": 13.779301766440422,
      "vol_1y": 26.42015862044379,
      "sharpe_1y": 2.31,
      "sortino_1y": 2.7,
      "max_drawdown": -42.7,
      "curr_drawdown": -10.1,
      "from_high": -10.294448190604642
    },
    "GOLD": {
      "price": 64.94,
      "one_yr_ret": 50.921653679996126,
      "ytd_ret": 9.203068522660839,
      "vol_1y": 24.796631584827665,
      "sharpe_1y": 1.89,
      "sortino_1y": 2.26,
      "max_drawdown": -91.6,
      "curr_drawdown": -56.3,
      "from_high": -10.6985698569857
    },
    "VGS": {
      "price": 142.29,
      "one_yr_ret": 8.787862870810637,
      "ytd_ret": -6.559625749855269,
      "vol_1y": 14.431504338328452,
      "sharpe_1y": 0.33,
      "sortino_1y": 0.42,
      "max_drawdown": -23.4,
      "curr_drawdown": -8.1,
      "from_high": -8.992644707387273
    },
    "GDX": {
      "price": 136.99,
      "one_yr_ret": 97.69317568344943,
      "ytd_ret": 2.975832796855493,
      "vol_1y": 41.972970923369566,
      "sharpe_1y": 2.23,
      "sortino_1y": 2.72,
      "max_drawdown": -44.7,
      "curr_drawdown": -19.9,
      "from_high": -21.719999999999995
    },
    "SEMI": {
      "price": 25.24,
      "one_yr_ret": 68.96606784037138,
      "ytd_ret": 8.027323461324688,
      "vol_1y": 34.317105274526035,
      "sharpe_1y": 1.89,
      "sortino_1y": 2.58,
      "max_drawdown": -38.9,
      "curr_drawdown": -7.2,
      "from_high": -8.71609403254973
    },
    "ASIA": {
      "price": 15.5,
      "one_yr_ret": 35.70406706427735,
      "ytd_ret": 1.408450974487585,
      "vol_1y": 26.28059902540405,
      "sharpe_1y": 1.21,
      "sortino_1y": 1.48,
      "max_drawdown": -59.6,
      "curr_drawdown": -9.4,
      "from_high": -7.957244655581946
    }
  },
  "verdicts": {
    "IVV": "Accumulate",
    "FANG": "Watch",
    "VAS": "Buy",
    "QAU": "Buy",
    "GOLD": "Buy",
    "VGS": "Accumulate",
    "GDX": "Hold",
    "SEMI": "Buy",
    "ASIA": "Buy"
  }
}