{
  "date": "2026-03-18",
  "etf_data": {
    "IVV": {
      "price": 63.22,
      "one_yr_ret": 7.666742592431475,
      "ytd_ret": -7.744103776745881,
      "vol_1y": 16.790937203753593,
      "sharpe_1y": 0.22,
      "sortino_1y": 0.29,
      "max_drawdown": -95.6,
      "curr_drawdown": -74.1,
      "from_high": -9.788812785388128
    },
    "FANG": {
      "price": 30.58,
      "one_yr_ret": 10.225694554759212,
      "ytd_ret": -12.8293180692999,
      "vol_1y": 26.74529150395235,
      "sharpe_1y": 0.23,
      "sortino_1y": 0.35,
      "max_drawdown": -42.1,
      "curr_drawdown": -21.1,
      "from_high": -20.736132711249354
    },
    "VAS": {
      "price": 107.88,
      "one_yr_ret": 13.210465885101218,
      "ytd_ret": -0.6558277022562953,
      "vol_1y": 12.992336138566362,
      "sharpe_1y": 0.71,
      "sortino_1y": 0.88,
      "max_drawdown": -35.8,
      "curr_drawdown": -5.8,
      "from_high": -5.575492341356678
    },
    "QAU": {
      "price": 39.68,
      "one_yr_ret": 64.22276734695541,
      "ytd_ret": 14.351059243732433,
      "vol_1y": 26.40934063845642,
      "sharpe_1y": 2.28,
      "sortino_1y": 2.66,
      "max_drawdown": -42.7,
      "curr_drawdown": -9.6,
      "from_high": -10.811418296246352
    },
    "GOLD": {
      "price": 64.34,
      "one_yr_ret": 46.78899596289525,
      "ytd_ret": 6.702234892370895,
      "vol_1y": 24.917726545845873,
      "sharpe_1y": 1.72,
      "sortino_1y": 2.06,
      "max_drawdown": -91.6,
      "curr_drawdown": -57.3,
      "from_high": -11.523652365236517
    },
    "VGS": {
      "price": 143.13,
      "one_yr_ret": 8.03783687302111,
      "ytd_ret": -6.9838859983959445,
      "vol_1y": 14.438498139031747,
      "sharpe_1y": 0.28,
      "sortino_1y": 0.36,
      "max_drawdown": -23.4,
      "curr_drawdown": -8.5,
      "from_high": -8.45538855132715
    },
    "GDX": {
      "price": 135.79,
      "one_yr_ret": 94.48843823414983,
      "ytd_ret": 4.191845398495286,
      "vol_1y": 41.90442237982231,
      "sharpe_1y": 2.16,
      "sortino_1y": 2.63,
      "max_drawdown": -44.7,
      "curr_drawdown": -18.9,
      "from_high": -22.40571428571429
    },
    "SEMI": {
      "price": 25.7,
      "one_yr_ret": 68.90803714629305,
      "ytd_ret": 8.32622013914197,
      "vol_1y": 34.31704128269647,
      "sharpe_1y": 1.89,
      "sortino_1y": 2.58,
      "max_drawdown": -38.9,
      "curr_drawdown": -6.9,
      "from_high": -7.052441229656417
    },
    "ASIA": {
      "price": 15.65,
      "one_yr_ret": 38.12972727565549,
      "ytd_ret": 3.9570768519511024,
      "vol_1y": 26.3818137595966,
      "sharpe_1y": 1.29,
      "sortino_1y": 1.6,
      "max_drawdown": -59.6,
      "curr_drawdown": -7.1,
      "from_high": -7.06650831353919
    }
  },
  "verdicts": {
    "IVV": "Accumulate",
    "FANG": "Watch",
    "VAS": "Buy",
    "QAU": "Buy",
    "GOLD": "Buy",
    "VGS": "Accumulate",
    "GDX": "Watch",
    "SEMI": "Buy",
    "ASIA": "Buy"
  }
}