{
  "date": "2026-03-13",
  "etf_data": {
    "IVV": {
      "price": 63.05,
      "one_yr_ret": 7.624911340028362,
      "ytd_ret": -8.15399806646051,
      "vol_1y": 16.76463440882125,
      "sharpe_1y": 0.22,
      "sortino_1y": 0.28,
      "max_drawdown": -95.6,
      "curr_drawdown": -74.2,
      "from_high": -10.031392694063928
    },
    "FANG": {
      "price": 30.77,
      "one_yr_ret": 10.463539287984736,
      "ytd_ret": -12.371128333326775,
      "vol_1y": 26.75522856488144,
      "sharpe_1y": 0.24,
      "sortino_1y": 0.36,
      "max_drawdown": -42.1,
      "curr_drawdown": -20.7,
      "from_high": -20.243649559357177
    },
    "VAS": {
      "price": 107.9,
      "one_yr_ret": 15.087355718312544,
      "ytd_ret": -0.46185109009218017,
      "vol_1y": 13.011750028047993,
      "sharpe_1y": 0.85,
      "sortino_1y": 1.05,
      "max_drawdown": -35.8,
      "curr_drawdown": -5.7,
      "from_high": -5.5579868708971505
    },
    "QAU": {
      "price": 40.61,
      "one_yr_ret": 71.42144738977368,
      "ytd_ret": 16.809608762331372,
      "vol_1y": 26.354318535743555,
      "sharpe_1y": 2.56,
      "sortino_1y": 2.97,
      "max_drawdown": -42.7,
      "curr_drawdown": -7.7,
      "from_high": -8.721060912564626
    },
    "GOLD": {
      "price": 66.18,
      "one_yr_ret": 53.95901892095234,
      "ytd_ret": 10.220075216570557,
      "vol_1y": 24.828249489660514,
      "sharpe_1y": 2.01,
      "sortino_1y": 2.41,
      "max_drawdown": -91.6,
      "curr_drawdown": -55.9,
      "from_high": -8.993399339933983
    },
    "VGS": {
      "price": 142.51,
      "one_yr_ret": 8.190490967703013,
      "ytd_ret": -7.499513732560981,
      "vol_1y": 14.41899446010221,
      "sharpe_1y": 0.29,
      "sortino_1y": 0.37,
      "max_drawdown": -23.4,
      "curr_drawdown": -9.0,
      "from_high": -8.851934761752482
    },
    "GDX": {
      "price": 144.45,
      "one_yr_ret": 113.79522942186907,
      "ytd_ret": 8.38369079699055,
      "vol_1y": 41.700781933117646,
      "sharpe_1y": 2.63,
      "sortino_1y": 3.22,
      "max_drawdown": -44.7,
      "curr_drawdown": -15.6,
      "from_high": -17.457142857142863
    },
    "SEMI": {
      "price": 25.02,
      "one_yr_ret": 72.15483364726174,
      "ytd_ret": 7.600344495503442,
      "vol_1y": 34.29163084677878,
      "sharpe_1y": 1.99,
      "sortino_1y": 2.7,
      "max_drawdown": -38.9,
      "curr_drawdown": -7.6,
      "from_high": -9.51175406871609
    },
    "ASIA": {
      "price": 15.05,
      "one_yr_ret": 37.86451133290656,
      "ytd_ret": 0.2682760715116306,
      "vol_1y": 26.35129345760758,
      "sharpe_1y": 1.29,
      "sortino_1y": 1.58,
      "max_drawdown": -59.6,
      "curr_drawdown": -10.4,
      "from_high": -10.629453681710208
    }
  },
  "verdicts": {
    "IVV": "Accumulate",
    "FANG": "Watch",
    "VAS": "Buy",
    "QAU": "Buy",
    "GOLD": "Buy",
    "VGS": "Accumulate",
    "GDX": "Accumulate",
    "SEMI": "Buy",
    "ASIA": "Buy"
  }
}